{
  "ATTACHMENTS": null,
  "JFULLX": {
    "JFULLTYPE": "file",
    "JFULLCONTENT": "臺灣橋頭地方法院刑事簡易判決\r\n114年度簡字第3396號\r\n聲  請  人  臺灣橋頭地方檢察署檢察官\r\n被      告  林聖賢\r\n\r\n\r\n\r\n上列被告因竊盜案件，經檢察官聲請以簡易判決處刑（114年度\r\n速偵字第1016號），本院判決如下：\r\n　　主　文\r\n林聖賢犯竊盜罪，處拘役拾日，如易科罰金，以新臺幣壹仟元折\r\n算壹日。\r\n　　事實及理由\r\n一、本案犯罪事實及證據均引用聲請簡易判決處刑書之記載（如\r\n    附件）。　　\r\n二、核被告林聖賢所為，係犯刑法第320條第1項之竊盜罪。\r\n三、本院審酌被告有多次竊盜前科，有法院前案紀錄表1份附卷\r\n    可考，仍貪圖不法利益，竊取814生鮮超市大社店內之百威\r\n    啤酒英國版6罐、青葉嚕肉飯罐頭2罐；惟念其坦承犯行，所\r\n    竊財物價值非鉅，且均已發還告訴代理人何孟佑，有贓物認\r\n    領保管單1份在卷可考（見警卷第61頁）；兼衡其自陳國中\r\n    肄業之教育程度，從事鐵工，家境貧寒等一切情狀，量處如\r\n    主文所示之刑，並諭知易科罰金之折算標準。 　\r\n四、被告竊得之百威啤酒英國版6罐、青葉嚕肉飯罐頭2罐，均已\r\n    發還告訴代理人，已如前述，爰均不予宣告沒收或追徵。\r\n五、依刑事訴訟法第449條第1項前段、第3項、第454條第2項，\r\n    逕以簡易判決處刑如主文。\r\n六、如不服本判決，得自收受送達之日起20日內，向本院提起上\r\n    訴（須附繕本），上訴於本院第二審合議庭。\r\n本案經檢察官洪若純聲請以簡易判決處刑。\r\n中　　華　　民　　國　　115 　年　　2 　　月　　23　　日\r\n　　　　　　　　　橋頭簡易庭　　法　官　黃逸寧\r\n以上正本，係照原本作成，證明與原本無異。\r\n如不服本判決，得自收受送達之翌日起20日內向本院提出上訴狀\r\n（須附繕本），上訴於本院之合議庭。\r\n中　　華　　民　　國　　115 　年　　2 　　月　　23　　日\r\n　　　　　　　　　　　　　　　　書記官　吳雅琪\r\n附錄法條：\r\n中華民國刑法第320條第1項\r\n意圖為自己或第三人不法之所有，而竊取他人之動產者，為竊盜\r\n罪，處5年以下有期徒刑、拘役或50萬元以下罰金。\r\n附件：\r\n臺灣橋頭地方檢察署檢察官聲請簡易判決處刑書\r\n　　　　　　　　　　　　　　　　　 114年度速偵字第1016號\r\n　　被　　　告　林聖賢　（年籍詳卷）\r\n上列被告因竊盜案件，業經偵查終結，認為宜聲請以簡易判決處\r\n刑，茲將犯罪事實及證據並所犯法條分敘如下：　　\r\n　　　　犯罪事實\r\n一、林聖賢意圖為自己不法之所有，基於竊盜之犯意，於民國11\r\n    4年9月17日16時38分許，在高雄市○○區○○路00○0號814生鮮\r\n    超市大社店，徒手竊取陳列在貨架上之百威啤酒英國版6罐\r\n    、青葉嚕肉飯罐頭2罐（共價值新臺幣276元），得手後藏放\r\n    於其個人之隨身袋子，未結帳即離去。嗣店員何孟佑當場發\r\n    現遭竊報警處理，員警到場扣得上開商品（均已發還），始\r\n    悉上情。\r\n二、案經814百貨生鮮超市大社店（殷郡有限公司）委由何孟佑\r\n    訴由高雄市政府警察局仁武分局報告偵辦。\r\n　　　　證據並所犯法條\r\n一、上揭犯罪事實，業據被告林聖賢於警詢及偵查時均坦承不諱\r\n    ，核與證人即告訴代理人何孟佑於警詢中之指訴情節相符，\r\n    並有高雄市政府警察局仁武分局搜索扣押筆錄、扣押物品目\r\n    錄表、扣押物品收據、贓物認領保管單各1份、監視器影像\r\n    擷取照片6張可資佐證，足認被告上開自白與事實相符，其\r\n    犯嫌已堪認定。\r\n二、核被告所為，係犯刑法第320條第1項之竊盜罪嫌。\r\n三、依刑事訴訟法第451條第1項聲請逕以簡易判決處刑。\r\n　　此　致\r\n臺灣橋頭地方法院\r\n中　　華　　民　　國　 114　　年　　9 　　月　　22　　日　　　　　　　　　　　　　　　檢　察　官　洪若純",
    "JFULLPDF": "https://data.judicial.gov.tw/jdg/api/JDocFile/CTDM/114%2c%e7%b0%a1%2c3396%2c20260223%2c1/pdf"
  },
  "JID": "CTDM,114,簡,3396,20260223,1",
  "JYEAR": "114",
  "JCASE": "簡",
  "JNO": "3396",
  "JDATE": "20260223",
  "JTITLE": "竊盜"
}