{
  "ATTACHMENTS": null,
  "JFULLX": {
    "JFULLTYPE": "file",
    "JFULLCONTENT": "臺灣高雄地方法院民事裁定\r\n114年度司執字第165295號\r\n債  權  人  和潤企業股份有限公司\r\n\r\n法定代理人  陳建州  \r\n\r\n\r\n債  務  人  楊淑蘭  \r\n\r\n上列當事人間清償票款強制執行事件，本院裁定如下：\r\n    主　　　　文\r\n本件移送臺灣橋頭地方法院。\r\n　　理　　　　由\r\n一、強制執行由應執行之標的物所在地或應為執行行為地之法院\r\n    管轄。強制執行法第7條第1項定有明文。又依同法第30條之\r\n    1準用民事訴訟法第28條第1項規定，強制執行之全部或一部\r\n    ，法院認為無管轄權者，應依債權人聲請或依職權以裁定移\r\n    送於其管轄法院。\r\n二、經查本件債權人聲請執行債務人所有坐落高雄市○○區○○段○○\r\n    段0000000地號土地及同地段428建號建物，另聲請執行債務\r\n    人對第三人中國信託商業銀行股份有限公司博愛分公司、左\r\n    營南站郵局之存款債權，均非本院轄區，揆諸首揭規定及說\r\n    明，本件應屬臺灣橋頭地方法院管轄，爰依職權將本件移送\r\n    該管轄法院。\r\n三、如不服本裁定，應於裁定送達後10日內，以書狀向司法事務\r\n　　官提出異議，並應繳納裁判費新臺幣1,000元。\r\n中　　華　　民　　國　 114　　年　　12　　月　　4 　　日\r\n　　　　　　　　　民事執行處　司法事務官  宋佳蓁",
    "JFULLPDF": "https://data.judicial.gov.tw/jdg/api/JDocFile/KSDV/114%2c%e5%8f%b8%e5%9f%b7%2c165295%2c20251204%2c1/pdf"
  },
  "JID": "KSDV,114,司執,165295,20251204,1",
  "JYEAR": "114",
  "JCASE": "司執",
  "JNO": "165295",
  "JDATE": "20251204",
  "JTITLE": "清償票款"
}