{
  "ATTACHMENTS": null,
  "JFULLX": {
    "JFULLTYPE": "file",
    "JFULLCONTENT": "臺灣新北地方法院刑事裁定  \r\n114年度易字第2180號\r\n115年度聲字第375號\r\n公  訴  人  臺灣新北地方檢察署檢察官\r\n聲  請  人  \r\n即  被  告  許建銘\r\n\r\n\r\n\r\n上列聲請人即被告因家暴傷害等案件，經檢察官提起公訴（114\r\n年度偵字第58601號），被告於本院準備程序中，就被訴事實為\r\n有罪之陳述，經本院合議庭裁定由受命法官獨任進行簡式審判程\r\n序，被告聲請具保停止羈押，裁定如下：\r\n　　主　文\r\n許建銘自民國壹佰壹拾伍年貳月拾貳日起撤銷羈押。\r\n具保停止羈押之聲請駁回。\r\n　　理　由\r\n一、聲請意旨略以：我對告訴人感到很抱歉，我安眠藥跟酒會戒\r\n    掉，不會再為類似的行為，我之後會搬出去住在我阿姨家，\r\n    請求予以交保等語。\r\n二、按羈押於其原因消滅時，應即撤銷羈押將被告釋放，刑事訴\r\n    訟法第107條第1項定有明文。查聲請人即被告許建銘因另案\r\n    竊盜案件，於民國115年2月12日起轉入法務部矯正署臺北監\r\n    獄臺北分監執行，此有臺灣新北地方檢察署檢察官115年度\r\n    執辛字第779號執行指揮書在卷可稽，是聲請人原羈押原因\r\n    應於上開執行之日消滅，聲請人之羈押自應予撤銷，爰裁定\r\n    如主文第1項所示。\r\n三、另聲請人雖聲請具保停止羈押，惟本院既已自115年2月12日\r\n    起撤銷羈押，則聲請人已非屬經本案審判中羈押之被告，與\r\n    刑事訴訟法第110條第1項之聲請要件不符，其所為之具保停\r\n    止羈押聲請，自無從准許，應予駁回，爰裁定如主文第2項\r\n    所示。\r\n四、依刑事訴訟法第107條第1項、第121條第1項、第220條，裁\r\n    定如主文。\r\n中　　華　　民　　國　　115 　年　　2 　　月　　13　　日\r\n　　　　　　　　　刑事第十五庭　法　官　施吟蒨\r\n以上正本證明與原本無異。\r\n如不服本裁定，應於收受送達後10日內向本院提出抗告狀。（應\r\n附繕本）\r\n　　　　　　　　　　　　　　　　書記官　陳靜怡\r\n中　　華　　民　　國　　115 　年　　2 　　月　　13　　日",
    "JFULLPDF": "https://data.judicial.gov.tw/jdg/api/JDocFile/PCDM/114%2c%e6%98%93%2c2180%2c20260213%2c2/pdf"
  },
  "JID": "PCDM,114,易,2180,20260213,2",
  "JYEAR": "114",
  "JCASE": "易",
  "JNO": "2180",
  "JDATE": "20260213",
  "JTITLE": "家暴傷害等"
}