{
  "ATTACHMENTS": null,
  "JFULLX": {
    "JFULLTYPE": "file",
    "JFULLCONTENT": "臺灣雲林地方法院民事裁定\r\n114年度港小字第234號\r\n原      告  王道國際理財顧問有限公司\r\n\r\n法定代理人  林御存  \r\n上列原告與被告陳佳鈺間請求給付服務報酬事件，本院裁定如下\r\n：\r\n　　主　文\r\n原告應於本裁定送達後5日內，補繳第一審裁判費新臺幣1,000元\r\n，逾期未補，即駁回其訴。\r\n　　理　由\r\n一、按起訴不合程式或不備其他要件者，法院應以裁定駁回之。\r\n    但其情形可以補正者，審判長應定期間先命補正，民事訴訟\r\n    法第249條第1項第6款定有明文，依同法第436條之23、第43\r\n    6條第2項規定，於小額訴訟程序準用之。另提起民事訴訟應\r\n    依民事訴訟法第1編第3章第1節、第2節之規定繳納裁判費，\r\n    此為法定必要之程式。\r\n二、本件原告起訴未據繳足裁判費，於法自有未合。查本件訴訟\r\n    標的金額為新臺幣（下同）18,000元，應徵收第一審裁判費\r\n    1,500元，扣除已繳納之500元，尚應補繳1,000元。茲依民\r\n    事訴訟法第436條之23、第436條第2項、第249條第1項但書\r\n    之規定，限原告於收受本裁定送達5日內補繳，逾期未補，\r\n    即駁回其訴，特此裁定。\r\n中華民國115年1月2日\r\n　　　　　　　　　北港簡易庭　　　法　官　尤光卉\r\n以上正本係照原本作成。\r\n本件不得抗告。\r\n中　　華　　民　　國　　115 　年　　1 　　月　　2 　　日\r\n　　　　　　　　　　　　　　　　　書記官　陳映佐",
    "JFULLPDF": "https://data.judicial.gov.tw/jdg/api/JDocFile/PKEV/114%2c%e6%b8%af%e5%b0%8f%2c234%2c20260102%2c1/pdf"
  },
  "JID": "PKEV,114,港小,234,20260102,1",
  "JYEAR": "114",
  "JCASE": "港小",
  "JNO": "234",
  "JDATE": "20260102",
  "JTITLE": "給付服務報酬"
}