{
  "ATTACHMENTS": null,
  "JFULLX": {
    "JFULLTYPE": "file",
    "JFULLCONTENT": "臺灣新竹地方法院刑事簡易判決\r\n114年度竹簡字第1262號\r\n聲  請  人  臺灣新竹地方檢察署檢察官\r\n被      告  劉興文\r\n\r\n\r\n\r\n\r\n上列被告因毀損案件，經檢察官聲請以簡易判決處刑（114年度\r\n偵字第8778號），本院判決如下：\r\n　　主　文\r\n劉興文犯毀損他人物品罪，處拘役肆拾日，如易科罰金，以新臺\r\n幣壹仟元折算壹日。\r\n　　事實及理由\r\n一、本案犯罪事實及證據，除證據增列「員警職務報告」外，餘\r\n    均引用檢察官聲請簡易判決處刑書之記載(如附件)。\r\n二、論罪科刑：\r\n　㈠核被告所為，係犯刑法第354條之毀損他人物品罪。\r\n　㈠爰以行為人之責任為基礎，審酌被告因飲酒後行為失控，竟\r\n    率爾毀損告訴人之車輛前保險桿，對他人財產權造成損害，\r\n    所為實屬不該；復考量被告犯後坦承犯行，惟具狀表明欲調\r\n    解卻拒不到庭，亦未與告訴人達成和解或給付賠償，兼衡本\r\n    案之犯罪動機、情節、告訴人所受財產損害等一切情狀，量\r\n    處如主文所示之刑，並諭知易科罰金之折算標準，以示懲儆\r\n    。\r\n三、依刑事訴訟法第449條第1項前段、第454條第2項，逕以簡易\r\n    判決處刑如主文。\r\n四、如不服本判決，得自收受送達之日起20日內向本院提出上訴\r\n    狀，上訴於本院第二審合議庭（須附繕本）。\r\n本案經檢察官沈郁智聲請以簡易判決處刑。\r\n中　　華　　民　　國　　115 　年　　2 　　月　 24　　日\r\n　　　　　　　　　新竹簡易庭　法　官　黃翊雯\r\n以上正本證明與原本無異。\r\n中　　華　　民　　國　　115 　年　　2 　　月　　25　　日\r\n　　　　　　　　　　　　　　　　書記官 王嘉蓉　　　　　　　　　\r\n附錄論罪科刑法條\r\n刑法第 354 條\r\n毀棄、損壞前二條以外之他人之物或致令不堪用，足以生損害於\r\n公眾或他人者，處二年以下有期徒刑、拘役或一萬五千元以下罰\r\n金。　\r\n　　　　　　　　　　　　　　　　　\r\n附件：\r\n臺灣新竹地方檢察署檢察官聲請簡易判決處刑書　\r\n　　　　　　　　　　　　　　　　　　 114年度偵字第8778號\r\n　　被　　　告　劉興文　\r\n\r\n上列被告因毀棄損壞等案件，業經偵查終結，認宜聲請以簡易判\r\n決處刑，茲將犯罪事實及證據並所犯法條分敘如下：\r\n　　　　犯罪事實\r\n一、劉興文基於毀損之犯意，於民國113年8月1日凌晨2時許，在\r\n    新竹市○區○○路0段000號前，以腳踹毀損蘇煥文所停放該處\r\n    車牌號碼000-0000號營業小客車，致使上開車輛前保險桿損\r\n    毀不堪使用，足以生損害於蘇煥文。\r\n二、案經蘇煥文訴由新竹市警察局第一分局報告偵辦。\r\n　　　　證據並所犯法條\r\n一、上揭犯罪事實，業據被告劉興文於偵查中坦承不諱，核與告\r\n    訴人蘇煥文於警詢及偵查中之指述情節相符，復有告訴人提\r\n    供之車輛修繕單、行照及台北市計程車客運業駕駛人自備車\r\n    輛參與經營契約書；新竹市北門派出所110報案紀錄單、車\r\n    輛詳細資料報表、現場暨車輛毀損照片、監視器影像擷取畫\r\n    面等在卷可稽，足認被告自白與事實相符，其犯嫌堪予認定\r\n    。\r\n二、核被告所為，係犯刑法第354條之毀棄損壞罪嫌。\r\n三、依刑事訴訟法第451條第1項聲請逕以簡易判決處刑。\r\n　　此　致\r\n臺灣新竹地方法院\r\n中　　華　　民　　國　　114 　年　　 10　　月　　22　 日　　　　　　　　　　　　　　　檢　察　官　 沈郁智本件證明與原本無異　　　　　　中　　華　　民　　國　　114 　年　　 11 　 月　　5　　日　　　　　　　　　　　　　　　書　記　官　 陳桂香",
    "JFULLPDF": "https://data.judicial.gov.tw/jdg/api/JDocFile/SCDM/114%2c%e7%ab%b9%e7%b0%a1%2c1262%2c20260224%2c1/pdf"
  },
  "JID": "SCDM,114,竹簡,1262,20260224,1",
  "JYEAR": "114",
  "JCASE": "竹簡",
  "JNO": "1262",
  "JDATE": "20260224",
  "JTITLE": "毀損"
}