{
  "ATTACHMENTS": null,
  "JFULLX": {
    "JFULLTYPE": "file",
    "JFULLCONTENT": "臺灣臺北地方法院刑事判決\r\n114年度審簡上字第158號\r\n上  訴  人  臺灣臺北地方檢察署檢察官\r\n被      告  蔡蓁  \r\n\r\n\r\n選任辯護人  蘇千祿律師(法扶律師)            \r\n上列上訴人因被告詐欺案件，不服本院民國114年5月2日所為114\r\n年度審簡字第707號第一審簡易判決(臺灣臺北地方檢察署檢察官\r\n起訴案號：113年度偵字第28674號)，提起上訴，本院管轄第二\r\n審之合議庭，判決如下：\r\n　　主　　　文\r\n上訴駁回。\r\n　　事實及理由\r\n一、審理範圍：\r\n(一)按刑事訴訟法第348條規定：「（第1項）上訴得對於判決之\r\n    一部為之。（第2項）對於判決之一部上訴者，其有關係之\r\n    部分，視為亦已上訴。但有關係之部分為無罪、免訴或不受\r\n    理者，不在此限。(第3項）上訴得明示僅就判決之刑、沒收\r\n    或保安處分一部為之。」刑事訴訟法第348條第3項之立法理\r\n    由指出：「為尊重當事人設定攻防之範圍，並減輕上訴審審\r\n    理之負擔，容許上訴權人僅針對刑、沒收或保安處分一部提\r\n    起上訴，其未表明上訴之認定犯罪事實部分，則不在第二審\r\n    之審判範圍。如為數罪併罰之案件，亦得僅針對各罪之刑、\r\n    沒收、保安處分或對併罰所定之應執行刑、沒收、保安處分\r\n    ，提起上訴，其效力不及於原審所認定之各犯罪事實，此部\r\n    分犯罪事實不在上訴審審查範圍」。是科刑事項已可不隨同\r\n    其犯罪事實而單獨成為上訴之標的，且上訴人明示僅就量刑\r\n    部分上訴時，第二審法院即不再就原審法院所認定之犯罪事\r\n    實為審查，而應以原審法院所認定之犯罪事實，作為論認原\r\n    審量刑妥適與否的判斷基礎。\r\n(二)本案上訴人即檢察官於本院審理時已表明僅針對刑的部分上\r\n    訴等語（見本院審簡上卷第89頁），業已明示僅就判決之刑\r\n    提起上訴，依刑事訴訟法第348條第3項規定及修法理由，本\r\n    院審理範圍限於原判決所處之刑，不及於原判決所認定事實\r\n    、罪名部分，本院以原審判決書所載之事實及罪名為基礎，\r\n    審究其諭知刑是否妥適，核先敘明。　\r\n二、刑之減輕事由\r\n　  被告蔡蓁以幫助他人犯罪之意思而參與犯罪構成要件以外之\r\n    行為，屬幫助犯，原審爰依刑法第30條第2項之規定，減輕\r\n    其刑。再被告於偵查坦認幫助洗錢事實，審理時自白前揭幫\r\n    助洗錢犯行，且無所得，原審爰依洗錢防制法第23條第3項\r\n    之規定，減輕其刑，並依法遞減輕之，核無違誤。　\r\n三、駁回上訴之理由：\r\n(一)檢察官上訴意旨略以：原審量處最低刑度有期徒刑2月顯屬\r\n    不當，請求撤銷原判決，改判處較重之刑等語。　　　\r\n(二)按關於刑之量定及緩刑之宣告，係實體法上賦予法院得為自\r\n    由裁量之事項，倘其未有逾越法律所規定之範圍，或濫用其\r\n    權限，即不得任意指摘為違法(最高法院75年台上字第7033\r\n    號判例意旨參照)。再按量刑輕重屬實體法賦予法院之自由\r\n    裁量權，此等職權之行使，在求具體個案不同情節之妥適，\r\n    倘法院於量刑時，已以行為人之責任為基礎，並斟酌刑法第\r\n    57條各款所列情狀，而未逾越法定範圍，又無明顯濫權情形\r\n    ，即不得任意指為違法(最高法院101年度台上字第1250號判\r\n    決意旨參照)。\r\n(三)經查，原審業已審酌被告提供金融帳戶資料供他人遂行詐欺\r\n    取財及洗錢之不法行為，使各告訴人財產法益受有損害，並\r\n    幫助掩飾犯罪贓款去向，實屬不該，兼衡其犯後坦承犯行、\r\n    迄未賠償告訴人5人所受損失（被告當庭自述現無賠償能力\r\n    ）之態度，兼衡被告於審理時自述高職畢業之智識程度、離\r\n    婚、有成年子女、現無業、經濟來源仰賴低收補助新臺幣(\r\n    下同)5,000元，租屋每月支出3,000元、無須扶養親人、領\r\n    有輕度身心障礙手冊等窘迫之生活狀況，暨其自述係為應徵\r\n    工作之犯罪動機、目的、手段、被告素行、參與犯罪之程度\r\n    及各告訴人所受損失金額高低、人數多寡等一切情狀，量處\r\n    如主文所示之刑，並分別諭知徒刑如易科罰金、罰金如易服\r\n    勞役之折算標準，足見原審係以被告之行為責任為量刑基礎\r\n    ，斟酌刑法第57條所列各款情形及其他量刑因子後，尤已考\r\n    量被告坦承犯行、未與告訴人達成和解等犯罪後之態度，及\r\n    告訴人因犯罪所受之損害，為整體評價而量處被告上開刑度\r\n    ，既無逾越法律所規定之範圍，亦無裁量權限之濫用，揆諸\r\n    前揭說明，原審量刑並無任何違法或不當之處。檢察官執前\r\n    揭上訴意旨提起上訴，核無理由，應予駁回。　　　\r\n據上論斷，應依刑事訴訟法第455條之1第1項、第3項、第368條\r\n、第373條，判決如主文。 \r\n本案經檢察官劉忠霖提起公訴，檢察官陳品妤提起上訴，檢察官\r\n謝承勳到庭執行職務。\r\n中　　華　　民　　國　　115 　年　　2 　　月　　24　　日\r\n　　　　　　　　　刑事第二十二庭　審判長法　官 莊書雯 　\r\n　　　　　　　　　　　　　　　　　　　　法　官 葉詩佳 　\r\n　　　　　　　　　　　　　　　　　　　　法　官 翁毓潔\r\n上正本證明與原本無異。\r\n不得上訴。\r\n　　　　　　　　　　　　　　　　　　　　 書記官 陽雅涵\r\n中　　華　　民　　國　　115 　年　　2 　　月　　24　　日",
    "JFULLPDF": "https://data.judicial.gov.tw/jdg/api/JDocFile/TPDM/114%2c%e5%af%a9%e7%b0%a1%e4%b8%8a%2c158%2c20260224%2c1/pdf"
  },
  "JID": "TPDM,114,審簡上,158,20260224,1",
  "JYEAR": "114",
  "JCASE": "審簡上",
  "JNO": "158",
  "JDATE": "20260224",
  "JTITLE": "洗錢防制法等"
}