{
  "ATTACHMENTS": null,
  "JFULLX": {
    "JFULLTYPE": "file",
    "JFULLCONTENT": "臺灣高等法院民事裁定\r\n115年度勞聲字第4號\r\n聲  請  人  郭恩惠  \r\n\r\n\r\n相  對  人  陳賴勇  \r\n上列當事人間確認僱傭關係不存在事件，聲請人聲請訴訟救助，\r\n本院裁定如下：\r\n　　主　文\r\n准予訴訟救助。\r\n　　理　由\r\n一、按當事人無資力支出訴訟費用者，法院應依聲請，以裁定准\r\n    予訴訟救助；民事訴訟法第107條第1項本文定有明文。又經\r\n    分會准予法律扶助之無資力者，其於訴訟程序中，向法院聲\r\n    請訴訟救助時，應准予訴訟救助，亦經法律扶助法第63條著\r\n    有明文。\r\n二、本件聲請人主張其因窘於生活，資力困難，實無籌措款項以\r\n    支出本件訴訟費用，並已向財團法人法律扶助基金會台北分\r\n    會申請法律扶助獲准在案等情，業據其提出財團法人法律扶\r\n    助基金會台北分會准予扶助證明書（全部扶助）、申請人資\r\n    力審查詢問表（見本院卷第5頁至第10頁）以資釋明，核其\r\n    所請於法尚無不合，應予准許。\r\n三、據上論結，本件聲請為有理由，爰裁定如主文。　\r\n中　　華　　民　　國　　115 　年　　2 　　月　　24　　日\r\n　　　　　　　　　勞動法庭\r\n　　　　　　　　　　　審判長法　官　 邱　琦\r\n　　　　　　　　　　　　　　法　官　 邱靜琪\r\n　　　　　　　　　　　　　　法　官　 高明德\r\n正本係照原本作成。\r\n如不服本裁定，應於收受送達後10日內向本院提出抗告狀，並應\r\n繳納抗告費新臺幣1500元。\r\n中　　華　　民　　國　　115 　年　　2 　　月　　24　　日\r\n\r\n　　　　　　　　　　　　　　書記官　 郭彥琪",
    "JFULLPDF": "https://data.judicial.gov.tw/jdg/api/JDocFile/TPHV/115%2c%e5%8b%9e%e8%81%b2%2c4%2c20260224%2c1/pdf"
  },
  "JID": "TPHV,115,勞聲,4,20260224,1",
  "JYEAR": "115",
  "JCASE": "勞聲",
  "JNO": "4",
  "JDATE": "20260224",
  "JTITLE": "訴訟救助"
}